[{"MonthName":"April","CustomerID":865,"Month":[4]},{"MonthName":"August","CustomerID":891,"Month":[8]},{"MonthName":"December","CustomerID":1310,"Month":[12]},{"MonthName":"February","CustomerID":763,"Month":[2]},{"MonthName":"January","CustomerID":727,"Month":[1]},{"MonthName":"July","CustomerID":963,"Month":[7]},{"MonthName":"June","CustomerID":1003,"Month":[6]},{"MonthName":"March","CustomerID":984,"Month":[3]},{"MonthName":"May","CustomerID":1058,"Month":[5]},{"MonthName":"November","CustomerID":1580,"Month":[11]},{"MonthName":"October","CustomerID":1305,"Month":[10]},{"MonthName":"September","CustomerID":1198,"Month":[9]}]